shtils/__init__.py
shtils/shtils.py
shtils-0.1.0a2.dist-info/METADATA
shtils-0.1.0a2.dist-info/WHEEL
shtils-0.1.0a2.dist-info/top_level.txt
shtils-0.1.0a2.dist-info/RECORD
